everai/__init__.py
everai/constants.py
everai/version.py
everai/api/__init__.py
everai/api/api.py
everai/api/patch_common_value.py
everai/app/__init__.py
everai/app/app.py
everai/app/app_manager.py
everai/app/app_runner.py
everai/app/app_runtime.py
everai/app/app_setup.py
everai/app/app_versioned.py
everai/app/autocaler_handler.py
everai/app/context.py
everai/app/service.py
everai/app/template.py
everai/app/typing.py
everai/app/volume_request.py
everai/commands/__init__.py
everai/commands/everai_cli.py
everai/commands/app/__init__.py
everai/commands/app/app.py
everai/commands/app/check.py
everai/commands/app/create.py
everai/commands/app/delete.py
everai/commands/app/events.py
everai/commands/app/get.py
everai/commands/app/list.py
everai/commands/app/pause.py
everai/commands/app/prepare.py
everai/commands/app/queue.py
everai/commands/app/resume.py
everai/commands/app/update.py
everai/commands/app/utils.py
everai/commands/auth/__init__.py
everai/commands/auth/login.py
everai/commands/auth/logout.py
everai/commands/autoscaler/__init__.py
everai/commands/autoscaler/autoscaler.py
everai/commands/command/__init__.py
everai/commands/command/command.py
everai/commands/command/decorator.py
everai/commands/command/list_utils.py
everai/commands/command/setup_subcommands.py
everai/commands/config/__init__.py
everai/commands/config/config.py
everai/commands/configmap/__init__.py
everai/commands/configmap/configmap.py
everai/commands/configmap/create.py
everai/commands/configmap/delete.py
everai/commands/configmap/get.py
everai/commands/configmap/list.py
everai/commands/configmap/update.py
everai/commands/image/__init__.py
everai/commands/image/build.py
everai/commands/image/image.py
everai/commands/namespace/__init__.py
everai/commands/namespace/create.py
everai/commands/namespace/delete.py
everai/commands/namespace/get.py
everai/commands/namespace/list.py
everai/commands/namespace/namespace.py
everai/commands/resources/__init__.py
everai/commands/resources/resources.py
everai-0.2.41.dist-info/licenses/LICENSE
everai-0.2.41.dist-info/METADATA
everai-0.2.41.dist-info/WHEEL
everai-0.2.41.dist-info/entry_points.txt
everai-0.2.41.dist-info/top_level.txt
everai-0.2.41.dist-info/RECORD
